chesscli/__init__.py
chesscli/__main__.py
chesscli/main.py
chesscli-0.2.8.dist-info/LICENSE
chesscli-0.2.8.dist-info/METADATA
chesscli-0.2.8.dist-info/WHEEL
chesscli-0.2.8.dist-info/entry_points.txt
chesscli-0.2.8.dist-info/top_level.txt
chesscli-0.2.8.dist-info/RECORD
