Metadata-Version: 2.1
Name: chesscli
Version: 0.2.8
Summary: A CLI tool for managing chess game development environment.
Author: Neel Patel
Requires-Python: >=3.7
License-File: LICENSE
Requires-Dist: typer
Requires-Dist: subprocess.run
